textwiser/__init__.py
textwiser/_version.py
textwiser/base.py
textwiser/factory.py
textwiser/options.py
textwiser/textwiser.py
textwiser/utils.py
textwiser/embeddings/__init__.py
textwiser/embeddings/bow.py
textwiser/embeddings/compound.py
textwiser/embeddings/doc2vec.py
textwiser/embeddings/random.py
textwiser/embeddings/tfidf.py
textwiser/embeddings/use.py
textwiser/embeddings/word.py
textwiser/transformations/__init__.py
textwiser/transformations/base.py
textwiser/transformations/lda.py
textwiser/transformations/nmf.py
textwiser/transformations/pool.py
textwiser/transformations/svd.py
textwiser/transformations/umap_.py
textwiser-2.0.2.dist-info/LICENSE
textwiser-2.0.2.dist-info/METADATA
textwiser-2.0.2.dist-info/NOTICES
textwiser-2.0.2.dist-info/WHEEL
textwiser-2.0.2.dist-info/top_level.txt
textwiser-2.0.2.dist-info/RECORD
