Metadata-Version: 2.1
Name: textwiser
Version: 2.0.2
Summary: TextWiser: Text Featurization Library
Home-page: https://github.com/fidelity/textwiser
Author: FMR LLC
Project-URL: Source, https://github.com/fidelity/textwiser
Project-URL: Documentation, https://fidelity.github.io/textwiser/
Classifier: License :: OSI Approved :: Apache Software License
Classifier: Programming Language :: Python :: 3.8
Classifier: Operating System :: OS Independent
Requires-Python: >=3.8
License-File: LICENSE
License-File: NOTICES
Requires-Dist: numpy
Requires-Dist: flair>=0.9
Requires-Dist: bpemb>=0.3.5
Requires-Dist: gensim>=4.0
Requires-Dist: scipy<1.13
Requires-Dist: scikit-learn>=0.23.2
Requires-Dist: torch>=1.1.0
Requires-Dist: transformers>=4.0
Provides-Extra: full
Requires-Dist: tensorflow>=2.0.0; extra == "full"
Requires-Dist: tensorflow-hub>=0.7.0; extra == "full"
Requires-Dist: umap-learn>=0.5.1; extra == "full"
